tobikodata/__init__.py
tobikodata/scheduler_facades/__init__.py
tobikodata/scheduler_facades/airflow.py
tobikodata/scheduler_facades/common.py
tobikodata/scheduler_facades/dagster.py
tobikodata/scheduler_facades/py.typed
tobiko_cloud_scheduler_facade-1.0.8.dist-info/METADATA
tobiko_cloud_scheduler_facade-1.0.8.dist-info/WHEEL
tobiko_cloud_scheduler_facade-1.0.8.dist-info/namespace_packages.txt
tobiko_cloud_scheduler_facade-1.0.8.dist-info/top_level.txt
tobiko_cloud_scheduler_facade-1.0.8.dist-info/RECORD
